odoo10_addon_website_sale_search_fuzzy-10.0.1.0.0-py2.7-nspkg.pth
odoo/addons/website_sale_search_fuzzy/README.rst
odoo/addons/website_sale_search_fuzzy/__init__.py
odoo/addons/website_sale_search_fuzzy/__manifest__.py
odoo/addons/website_sale_search_fuzzy/hooks.py
odoo/addons/website_sale_search_fuzzy/controllers/__init__.py
odoo/addons/website_sale_search_fuzzy/controllers/main.py
odoo/addons/website_sale_search_fuzzy/static/description/icon.png
odoo/addons/website_sale_search_fuzzy/tests/__init__.py
odoo/addons/website_sale_search_fuzzy/tests/test_hooks.py
odoo/addons/website_sale_search_fuzzy/tests/test_main.py
odoo10_addon_website_sale_search_fuzzy-10.0.1.0.0.dist-info/DESCRIPTION.rst
odoo10_addon_website_sale_search_fuzzy-10.0.1.0.0.dist-info/METADATA
odoo10_addon_website_sale_search_fuzzy-10.0.1.0.0.dist-info/RECORD
odoo10_addon_website_sale_search_fuzzy-10.0.1.0.0.dist-info/WHEEL
odoo10_addon_website_sale_search_fuzzy-10.0.1.0.0.dist-info/metadata.json
odoo10_addon_website_sale_search_fuzzy-10.0.1.0.0.dist-info/namespace_packages.txt
odoo10_addon_website_sale_search_fuzzy-10.0.1.0.0.dist-info/top_level.txt
